gmon/__init__.py
gmon/cli.py
gmon/utils.py
gmon/clients/__init__.py
gmon/clients/account.py
gmon/clients/monitoring.py
gmon/clients/service_monitoring.py
gmon/clients/utils.py
gmon-1.1.2.dist-info/METADATA
gmon-1.1.2.dist-info/WHEEL
gmon-1.1.2.dist-info/entry_points.txt
gmon-1.1.2.dist-info/top_level.txt
gmon-1.1.2.dist-info/RECORD
