Metadata-Version: 2.1
Name: gmon
Version: 1.1.2
Summary: Cloud Monitoring API client (unofficial)
Home-page: UNKNOWN
Author: Google Inc.
Author-email: ocervello@google.com
License: UNKNOWN
Keywords: cloud monitoring account metrics dashboards slo gcp
Platform: UNKNOWN
Classifier: Development Status :: 3 - Alpha
Classifier: Intended Audience :: Developers
Classifier: Topic :: Software Development :: Build Tools
Classifier: License :: OSI Approved :: MIT License
Classifier: Programming Language :: Python :: 3
Classifier: Programming Language :: Python :: 3.4
Classifier: Programming Language :: Python :: 3.5
Classifier: Programming Language :: Python :: 3.6
Requires-Python: >=3.4
Requires-Dist: google-api-python-client
Requires-Dist: google-cloud-core
Requires-Dist: oauth2client
Requires-Dist: google-cloud-monitoring
Requires-Dist: dotmap
